Metadata-Version: 2.1
Name: egen111222new-projecttample
Version: 1.0
Summary: New Description
Home-page: http://ukr.net
Author: Kirill
Author-email: egen13@ukr.net
License: UNKNOWN
Platform: UNKNOWN
